bellasplit/__init__.py
bellasplit/base_split.py
bellasplit/constants.py
bellasplit/database.py
bellasplit/filter.py
bellasplit/types.py
bellasplit/utils.py
bellasplit-1.1.0.dist-info/licenses/LICENSE
bellasplit-1.1.0.dist-info/METADATA
bellasplit-1.1.0.dist-info/WHEEL
bellasplit-1.1.0.dist-info/top_level.txt
bellasplit-1.1.0.dist-info/RECORD
