Metadata-Version: 2.4
Name: bellasplit
Version: 1.1.0
Summary: Creating splits of whole slide image scan data for digital pathology deep learning applications
Author-email: Paul Huettl <paulhuettl@web.de>
Maintainer-email: Paul Huettl <paulhuettl@web.de>, Lukas Wolfseher <lukas.wolfseher@informatik.uni-regensburg.de>
License-Expression: MIT
Project-URL: Source, https://github.com/spang-lab/bellasplit
Classifier: Programming Language :: Python :: 3
Classifier: Operating System :: OS Independent
Requires-Python: >=3.10
License-File: LICENSE
Requires-Dist: pandas>=2.0.0
Requires-Dist: pamly>=0.3.3
Requires-Dist: python-dotenv>=1.0.0
Requires-Dist: ruamel.yaml>=0.18.0
Requires-Dist: bellameta>=1.2.2
Dynamic: license-file
